terminology/__init__.py
terminology/ansi.py
terminology/asap_print.py
terminology/clear_line.py
terminology/status.py
terminology/terminal_width.py
terminology-1.0.16.dist-info/LICENSE
terminology-1.0.16.dist-info/WHEEL
terminology-1.0.16.dist-info/METADATA
terminology-1.0.16.dist-info/RECORD
