Metadata-Version: 2.1
Name: terminology
Version: 1.0.16
Summary: An intuitive way to color terminal text
Home-page: https://github.com/juanrgon/terminology
License: MIT
Author: Juan Gonzalez
Author-email: jrg2156@gmail.com
Requires-Python: >=2.7, !=3.0.*, !=3.1.*, !=3.2.*, !=3.3.*, !=3.4.*, !=3.5.*
Classifier: License :: OSI Approved :: MIT License
Classifier: Programming Language :: Python :: 2
Classifier: Programming Language :: Python :: 2.7
Classifier: Programming Language :: Python :: 3
Classifier: Programming Language :: Python :: 3.6
Classifier: Programming Language :: Python :: 3.7
Project-URL: Repository, https://github.com/juanrgon/terminology
